calrissian/__about__.py
calrissian/__init__.py
calrissian/context.py
calrissian/executor.py
calrissian/job.py
calrissian/k8s.py
calrissian/main.py
calrissian/report.py
calrissian/retry.py
calrissian/tool.py
calrissian/version.py
calrissian-0.18.1.dist-info/METADATA
calrissian-0.18.1.dist-info/WHEEL
calrissian-0.18.1.dist-info/entry_points.txt
calrissian-0.18.1.dist-info/licenses/LICENSE
calrissian-0.18.1.dist-info/RECORD
