Metadata-Version: 2.3
Name: calrissian
Version: 0.18.1
Summary: CWL runner for Kubernetes
Project-URL: Documentation, https://github.com/Duke-GCB/calrissian#readme
Project-URL: Issues, https://github.com/Duke-GCB/calrissian/issues
Project-URL: Source, https://github.com/Duke-GCB/calrissian
Author: Daniel Leehr, John Bradley, Emmanuel Mathot
Author-email: Fabrice Brito <fabrice.brito@terradue.com>
License: MIT
Classifier: Development Status :: 4 - Beta
Classifier: Environment :: Console
Classifier: Intended Audience :: Developers
Classifier: Programming Language :: Python
Classifier: Programming Language :: Python :: 3.8
Classifier: Programming Language :: Python :: 3.9
Classifier: Programming Language :: Python :: 3.10
Classifier: Programming Language :: Python :: 3.11
Classifier: Programming Language :: Python :: 3.12
Classifier: Programming Language :: Python :: Implementation :: CPython
Classifier: Programming Language :: Python :: Implementation :: PyPy
Requires-Python: >=3.8
Requires-Dist: cwltool==3.1.20240708091337
Requires-Dist: freezegun==1.2.2
Requires-Dist: importlib-metadata==6.8.0
Requires-Dist: kubernetes==28.1.0
Requires-Dist: msgpack==1.0.7
Requires-Dist: setuptools==70.0.0
Requires-Dist: tenacity==8.2.3
Requires-Dist: typing-extensions==4.8.0
Requires-Dist: urllib3==1.26.18
